cdktf_cdktf_provider_dnsimple/__init__.py
cdktf_cdktf_provider_dnsimple/py.typed
cdktf_cdktf_provider_dnsimple/_jsii/__init__.py
cdktf_cdktf_provider_dnsimple/_jsii/provider-dnsimple@10.1.0.jsii.tgz
cdktf_cdktf_provider_dnsimple/contact/__init__.py
cdktf_cdktf_provider_dnsimple/data_dnsimple_certificate/__init__.py
cdktf_cdktf_provider_dnsimple/data_dnsimple_registrant_change_check/__init__.py
cdktf_cdktf_provider_dnsimple/data_dnsimple_zone/__init__.py
cdktf_cdktf_provider_dnsimple/domain/__init__.py
cdktf_cdktf_provider_dnsimple/domain_delegation/__init__.py
cdktf_cdktf_provider_dnsimple/ds_record/__init__.py
cdktf_cdktf_provider_dnsimple/email_forward/__init__.py
cdktf_cdktf_provider_dnsimple/lets_encrypt_certificate/__init__.py
cdktf_cdktf_provider_dnsimple/provider/__init__.py
cdktf_cdktf_provider_dnsimple/registered_domain/__init__.py
cdktf_cdktf_provider_dnsimple/zone/__init__.py
cdktf_cdktf_provider_dnsimple/zone_record/__init__.py
cdktf_cdktf_provider_dnsimple-10.1.0.dist-info/LICENSE
cdktf_cdktf_provider_dnsimple-10.1.0.dist-info/METADATA
cdktf_cdktf_provider_dnsimple-10.1.0.dist-info/WHEEL
cdktf_cdktf_provider_dnsimple-10.1.0.dist-info/top_level.txt
cdktf_cdktf_provider_dnsimple-10.1.0.dist-info/RECORD
